{"cameraMode":{"drawMode":0,"name":"Shaded","section":"Shading Mode"},"sceneLighting":true,"audioPlay":false,"sceneViewState":{"m_AlwaysRefresh":false,"showFog":true,"showSkybox":true,"showFlares":true,"showImageEffects":true,"showParticleSystems":true,"showVisualEffectGraphs":true,"m_FxEnabled":false},"in2DMode":false,"pivot":{"x":188.1128387451172,"y":-42.664188385009769,"z":-22.57845115661621},"rotation":{"x":-0.077681764960289,"y":-0.7352954149246216,"z":0.08554951101541519,"w":-0.6678891181945801},"size":99.50875854492188,"orthographic":false}